{
  "vue-name": {
    "prefix": "vname",
    "body": [
      "name: '$1',"
    ]
  },
  "vue-inheritAttrs": {
    "prefix": "vinheritAttrs",
    "body": [
      "inheritAttrs: ${1:false},"
    ]
  },
  "vue-components": {
    "prefix": "vcomponents",
    "body": [
      "components: {",
      "  $1",
      "},"
    ]
  },
  "vue-data": {
    "prefix": "vdata",
    "body": [
      "data() {",
      "  return {",
      "    $1",
      "  }",
      "},"
    ]
  },
  "vue-props": {
    "prefix": "vprops",
    "body": [
      "props: {",
      "  $1: {",
      "    type: $2,",
      "  },",
      "},"
    ]
  },
  "vue-computed": {
    "prefix": "vcomputed",
    "body": [
      "computed: {",
      " $1() {",
      "    return $2",
      "  }",
      "},"
    ]
  },
  "vue-methods": {
    "prefix": "vmethods",
    "body": [
      "methods: {",
      "  $1() {",
      "    $2",
      "  }",
      "},"
    ]
  },
  "vue-watch": {
    "prefix": "vwatch",
    "body": [
      "watch: {",
      "  data(newValue, oldValue) {",
      "    $1",
      "  }",
      "},"
    ]
  }
}